maggport/__init__.py
maggport/__main__.py
maggport/exports.py
maggport/logger.py
maggport/maggport.py
maggport/validate.py
maggport-1.0.4.dist-info/LICENSE
maggport-1.0.4.dist-info/METADATA
maggport-1.0.4.dist-info/WHEEL
maggport-1.0.4.dist-info/entry_points.txt
maggport-1.0.4.dist-info/top_level.txt
maggport-1.0.4.dist-info/RECORD
