Metadata-Version: 2.1
Name: maggport
Version: 1.0.4
Summary: A mongodb aggregate export tool
Home-page: https://github.com/ccavales3/maggport
Author: Caesar Cavales
Author-email: c.cavales3@gmail.com
License: MIT
Platform: UNKNOWN
Requires-Dist: click (==8.0.1)
Requires-Dist: pymongo (==3.11.4)
Requires-Dist: pandas (==1.2.1)
